cubicweb_saem_ref/__init__.py
cubicweb_saem_ref/__pkginfo__.py
cubicweb_saem_ref/ark.py
cubicweb_saem_ref/ccplugin.py
cubicweb_saem_ref/hooks.py
cubicweb_saem_ref/pg_trgm.py
cubicweb_saem_ref/pviews.py
cubicweb_saem_ref/schema.py
cubicweb_saem_ref/site_cubicweb.py
cubicweb_saem_ref/uiprops.py
cubicweb_saem_ref/workflows.py
cubicweb_saem_ref/data/bandeau_saem.jpg
cubicweb_saem_ref/data/bx_metro.jpg
cubicweb_saem_ref/data/cd33.jpg
cubicweb_saem_ref/data/cubes.saem_ref.css
cubicweb_saem_ref/data/cubes.saem_ref.js
cubicweb_saem_ref/data/cubicweb.autocompletesearch.js
cubicweb_saem_ref/data/jquery.expander.js
cubicweb_saem_ref/data/jquery.highlight.js
cubicweb_saem_ref/data/jquery.jOrgChart.css
cubicweb_saem_ref/data/jquery.jOrgChart.js
cubicweb_saem_ref/data/logo_saem.png
cubicweb_saem_ref/data/mairie_bx.jpg
cubicweb_saem_ref/entities/__init__.py
cubicweb_saem_ref/entities/container.py
cubicweb_saem_ref/entities/eac.py
cubicweb_saem_ref/entities/oai.py
cubicweb_saem_ref/entities/org.py
cubicweb_saem_ref/entities/rdf.py
cubicweb_saem_ref/entities/seda.py
cubicweb_saem_ref/entities/skos.py
cubicweb_saem_ref/i18n/en.po
cubicweb_saem_ref/i18n/fr.po
cubicweb_saem_ref/i18n/static-messages.pot
cubicweb_saem_ref/migration/0.12.0_Any.py
cubicweb_saem_ref/migration/0.12.2_Any.py
cubicweb_saem_ref/migration/0.13.0_Any.py
cubicweb_saem_ref/migration/0.13.1_Any.py
cubicweb_saem_ref/migration/0.14.0_Any.py
cubicweb_saem_ref/migration/0.14.3_Any.py
cubicweb_saem_ref/migration/0.15.0_Any.py
cubicweb_saem_ref/migration/0.15.1_Any.py
cubicweb_saem_ref/migration/0.15.3_Any.py
cubicweb_saem_ref/migration/0.15.4_Any.py
cubicweb_saem_ref/migration/0.17.0_Any.py
cubicweb_saem_ref/migration/0.18.0_Any.py
cubicweb_saem_ref/migration/0.20.0_Any.py
cubicweb_saem_ref/migration/0.20.1_Any.py
cubicweb_saem_ref/migration/0.20.3_Any.py
cubicweb_saem_ref/migration/0.20.5_Any.py
cubicweb_saem_ref/migration/0.21.0_Any.py
cubicweb_saem_ref/migration/0.22.0_Any.py
cubicweb_saem_ref/migration/postcreate.py
cubicweb_saem_ref-1.0.2.dist-info/METADATA
cubicweb_saem_ref-1.0.2.dist-info/WHEEL
cubicweb_saem_ref-1.0.2.dist-info/entry_points.txt
cubicweb_saem_ref-1.0.2.dist-info/top_level.txt
cubicweb_saem_ref-1.0.2.dist-info/RECORD
